{
  "db_name": "SQLite",
  "query": "\n        INSERT INTO pages (title, text, created_at, updated_at)\n        VALUES ($1, $2, $3, $3)\n        RETURNING *\n        ",
  "describe": {
    "columns": [
      {
        "name": "id",
        "ordinal": 0,
        "type_info": "Int64"
      },
      {
        "name": "title",
        "ordinal": 1,
        "type_info": "Text"
      },
      {
        "name": "text",
        "ordinal": 2,
        "type_info": "Text"
      },
      {
        "name": "created_at",
        "ordinal": 3,
        "type_info": "Datetime"
      },
      {
        "name": "updated_at",
        "ordinal": 4,
        "type_info": "Datetime"
      }
    ],
    "parameters": {
      "Right": 3
    },
    "nullable": [
      false,
      false,
      false,
      false,
      false
    ]
  },
  "hash": "a159968db2ff2b7a987fc80154672d36288b553e44b0724979b2f048c50b20ce"
}
